ddom/__init__.py
ddom/data/cisco/chassis/n2k-c2248tp-e-1ge.yaml
ddom/data/cisco/chassis/n2k-c2348upq-10ge.yaml
ddom/data/cisco/chassis/n2k.yaml
ddom/data/cisco/chassis/n5k-c56128p.yaml
ddom/data/cisco/chassis/n5k-c5672up.yaml
ddom/data/cisco/chassis/n5k.yaml
ddom/data/cisco/chassis/n6k-c6001-64p.yaml
ddom/data/cisco/chassis/n6k-c6004.yaml
ddom/data/cisco/chassis/n77-c7706.yaml
ddom/data/cisco/chassis/n9k-c9396px.yaml
ddom/data/cisco/chassis/n9k.yaml
ddom/data/cisco/fab/n77-c7706-fab-2.yaml
ddom/data/cisco/fan/n2k-2348upq-fan-b.yaml
ddom/data/cisco/fan/n2k-2348upq-fan-f.yaml
ddom/data/cisco/fan/n2k-c2248-fan-b.yaml
ddom/data/cisco/fan/n2k-c2248-fan.yaml
ddom/data/cisco/fan/n56128-fan-b.yaml
ddom/data/cisco/fan/n56128-fan-f.yaml
ddom/data/cisco/fan/n6k-c6001-fan-b.yaml
ddom/data/cisco/fan/n6k-c6001-fan-f.yaml
ddom/data/cisco/fan/n6k-c6004-fan-b.yaml
ddom/data/cisco/fan/n6k-c6004-fan-f.yaml
ddom/data/cisco/fan/n77-c7706-fan.yaml
ddom/data/cisco/fan/n9k-c9300-fan2.yaml
ddom/data/cisco/linecard/n56-m24up2q.yaml
ddom/data/cisco/linecard/n5k-c5672up-m6q.yaml
ddom/data/cisco/linecard/n6004-m12q.yaml
ddom/data/cisco/linecard/n6k-c6001-m4q.yaml
ddom/data/cisco/linecard/n77-f324fq-25.yaml
ddom/data/cisco/linecard/n77-f348xp-23.yaml
ddom/data/cisco/linecard/n9k-c9396px.yaml
ddom/data/cisco/linecard/n9k-m12pq.yaml
ddom/data/cisco/powersupply/n2200-pac-400w-b.yaml
ddom/data/cisco/powersupply/n2200-pac-400w.yaml
ddom/data/cisco/powersupply/n2200-pdc-350w-b.yaml
ddom/data/cisco/powersupply/n77-dc-3kw.yaml
ddom/data/cisco/powersupply/n9k-pac-650w.yaml
ddom/data/cisco/powersupply/nxa-pac-1100w-b.yaml
ddom/data/cisco/powersupply/nxa-pac-1100w.yaml
ddom/data/cisco/supervisor/n2k-c2248tp-e-1ge.yaml
ddom/data/cisco/supervisor/n2k-c2348upq-10ge.yaml
ddom/data/cisco/supervisor/n5k-c56128p.yaml
ddom/data/cisco/supervisor/n5k-c5672up.yaml
ddom/data/cisco/supervisor/n6k-c6001-64p.yaml
ddom/data/cisco/supervisor/n6k-c6004.yaml
ddom/data/cisco/supervisor/n77-sup2e.yaml
ddom-0.3.1.dist-info/LICENSE
ddom-0.3.1.dist-info/METADATA
ddom-0.3.1.dist-info/WHEEL
ddom-0.3.1.dist-info/top_level.txt
ddom-0.3.1.dist-info/RECORD
