Metadata-Version: 2.1
Name: ddom
Version: 0.3.1
Summary: UNKNOWN
Home-page: https://github.com/jinjamator/ddom
Author: Wilhelm Putz
Author-email: jinjamator@aci.guru
License: ASL V2
Platform: UNKNOWN
Classifier: License :: OSI Approved :: Apache Software License
Classifier: Programming Language :: Python :: 3.8
Classifier: Topic :: System :: Installation/Setup
Classifier: Topic :: System :: Systems Administration
Classifier: Topic :: Utilities
Requires-Python: >=3.8
License-File: LICENSE
Requires-Dist: deepmerge
